swift_actor_critic.cpython-38-x86_64-linux-gnu.so
swiftac/__init__.py
swiftac/_version.py
swiftac/libswift-actor-critic-static.a
swiftac/include/swiftac.h
swiftac-0.1.8.dist-info/METADATA
swiftac-0.1.8.dist-info/WHEEL
swiftac-0.1.8.dist-info/RECORD
