Metadata-Version: 2.2
Name: swiftac
Version: 0.1.8
Summary: SwiftAC
Author: Khurram Javed
License: MIT
Classifier: Programming Language :: Python :: 3
Classifier: Programming Language :: C++
Classifier: Operating System :: OS Independent
Project-URL: Homepage, https://github.com/khurramjaved96/SwiftTD
Requires-Python: >=3.7
